conmap/__init__.py
conmap/api.py
conmap/cache.py
conmap/cli.py
conmap/config.py
conmap/discovery.py
conmap/logging.py
conmap/models.py
conmap/network.py
conmap/py.typed
conmap/reporting.py
conmap/scanner.py
conmap/utils.py
conmap/vulnerabilities/chain_detector.py
conmap/vulnerabilities/llm_analyzer.py
conmap/vulnerabilities/safe_mcp_detector.py
conmap/vulnerabilities/schema_inspector.py
conmap-0.5.0.dist-info/METADATA
conmap-0.5.0.dist-info/WHEEL
conmap-0.5.0.dist-info/entry_points.txt
conmap-0.5.0.dist-info/top_level.txt
conmap-0.5.0.dist-info/RECORD
