Metadata-Version: 2.4
Name: conmap
Version: 0.5.0
Summary: Subnet MCP endpoint discovery and vulnerability analysis toolkit with CLI and API interfaces.
Author-email: Armoriq <engineering@armoriq.io>
License: MIT
Keywords: mcp,security,scanner,model-context-protocol,network
Classifier: Programming Language :: Python :: 3
Classifier: Programming Language :: Python :: 3.9
Classifier: Programming Language :: Python :: 3.10
Classifier: Programming Language :: Python :: 3.11
Classifier: Programming Language :: Python :: 3.12
Classifier: License :: OSI Approved :: MIT License
Classifier: Operating System :: OS Independent
Classifier: Topic :: Security
Classifier: Topic :: System :: Networking
Requires-Python: >=3.9
Requires-Dist: async-timeout>=4.0
Requires-Dist: cachetools>=5.3
Requires-Dist: fastapi>=0.110
Requires-Dist: httpx[http2]>=0.27
Requires-Dist: netifaces>=0.11
Requires-Dist: openai>=1.14
Requires-Dist: pydantic>=2.6
Requires-Dist: rich>=13.7
Requires-Dist: typer[all]>=0.9
Requires-Dist: uvicorn[standard]>=0.29
Provides-Extra: dev
Requires-Dist: pytest>=7.4; extra == "dev"
Requires-Dist: pytest-cov>=4.1; extra == "dev"
Requires-Dist: pytest-asyncio>=0.23; extra == "dev"
Requires-Dist: respx>=0.21; extra == "dev"
Requires-Dist: ruff>=0.3; extra == "dev"
Requires-Dist: coverage[toml]>=7.4; extra == "dev"
Requires-Dist: pre-commit>=3.7; extra == "dev"
Requires-Dist: build>=1.2; extra == "dev"
Requires-Dist: bandit>=1.7; extra == "dev"
Requires-Dist: pip-audit>=2.7; extra == "dev"
Requires-Dist: cyclonedx-bom>=3.13; extra == "dev"
